Level1/dev.v
module dev(
    input wire signed [19:0] SP_out, // Input from softplus module
    
    output wire signed [19:0] D_out // Output from dev module
);

    // Linear approximation parameters (y = Mx + C)

        // Region 0: 0             < SP_out ≤ 2^-15         ; M = 192 = 2^7 + 2^6       ; C = 20'sh00000
        // Region 1: 2^-15         < SP_out ≤ 2^-13 + 2^-14 ; M = 48  = 2^5 + 2^4       ; C = 20'sh000A7
        // Region 2: 2^-13 + 2^-14 < SP_out ≤ 2^-12 + 2^-14 ; M = 32  = 2^5             ; C = 20'sh00105
        // Region 3: 2^-12 + 2^-14 < SP_out ≤ 2^-11         ; M = 26  = 2^4 + 2^3 + 2^1 ; C = 20'sh00140
        // Region 4: 2^-11         < SP_out ≤ 2^-11 + 2^-12 ; M = 20  = 2^4 + 2^2       ; C = 20'sh001A0
        // Region 5: 2^-11 + 2^-12 < SP_out ≤ 2^-10 + 2^-12 ; M = 16  = 2^4             ; C = 20'sh00200
        // Region 6: 2^-10 + 2^-12 < SP_out ≤ 2^-9  + 2^-12 ; M = 12  = 2^3 + 2^2       ; C = 20'sh002A0
        // Region 7: 2^-9  + 2^-12 < SP_out < INF           ; M = 10  = 2^3 + 2^1       ; C = 20'sh00330 (accurate up to 0.003)
    
    assign D_out = (SP_out <= 20'sh00001) ? (SP_out << 7) + (SP_out << 6)                              : // Region 0
                   (SP_out <= 20'sh00006) ? (SP_out << 5) + (SP_out << 4) + 20'sh000A7                 : // Region 1
                   (SP_out <= 20'sh0000A) ? (SP_out << 5) + 20'sh00105                                 : // Region 2
                   (SP_out <= 20'sh00010) ? (SP_out << 4) + (SP_out << 3) + (SP_out << 1) + 20'sh00140 : // Region 3
                   (SP_out <= 20'sh00018) ? (SP_out << 4) + (SP_out << 2) + 20'sh001A0                 : // Region 4
                   (SP_out <= 20'sh00028) ? (SP_out << 4) + 20'sh00200                                 : // Region 5
                   (SP_out <= 20'sh00048) ? (SP_out << 3) + (SP_out << 2) + 20'sh002A0                 : // Region 6
                                            (SP_out << 3) + (SP_out << 1) + 20'sh00330;                  // Region 7

endmodule

Level1/dev_tb.v
`include "dev.v"

module dev_tb;

    reg signed [19:0] INPUT;

    wire signed [19:0] OUTPUT;

    dev dev1(
        .SP_out(INPUT),
        
        .D_out(OUTPUT)
    );
    
    initial begin
        $dumpfile("dev_tb.vcd");
        $dumpvars(0, dev_tb);

        INPUT = 20'sh00000;

        #7;

        repeat(96)
        begin
            INPUT += 20'sh00001;
            #7;
        end
    end

endmodule

Level1/dev_tb.vcd
$date
	Wed Dec 11 14:27:57 2024
$end
$version
	Icarus Verilog
$end
$timescale
	1s
$end
$scope module dev_tb $end
$var wire 20 ! OUTPUT [19:0] $end
$var reg 20 " INPUT [19:0] $end
$scope module dev1 $end
$var wire 20 # SP_out [19:0] $end
$var wire 20 $ D_out [19:0] $end
$upscope $end
$upscope $end
$enddefinitions $end
$comment Show the parameter values. $end
$dumpall
$end
#0
$dumpvars
b0 $
b0 #
b0 "
b0 !
$end
#7
b11000000 !
b11000000 $
b1 "
b1 #
#14
b100000111 !
b100000111 $
b10 "
b10 #
#21
b100110111 !
b100110111 $
b11 "
b11 #
#28
b101100111 !
b101100111 $
b100 "
b100 #
#35
b110010111 !
b110010111 $
b101 "
b101 #
#42
b111000111 !
b111000111 $
b110 "
b110 #
#49
b111100101 !
b111100101 $
b111 "
b111 #
#56
b1000000101 !
b1000000101 $
b1000 "
b1000 #
#63
b1000100101 !
b1000100101 $
b1001 "
b1001 #
#70
b1001000101 !
b1001000101 $
b1010 "
b1010 #
#77
b1001011110 !
b1001011110 $
b1011 "
b1011 #
#84
b1001111000 !
b1001111000 $
b1100 "
b1100 #
#91
b1010010010 !
b1010010010 $
b1101 "
b1101 #
#98
b1010101100 !
b1010101100 $
b1110 "
b1110 #
#105
b1011000110 !
b1011000110 $
b1111 "
b1111 #
#112
b1011100000 !
b1011100000 $
b10000 "
b10000 #
#119
b1011110100 !
b1011110100 $
b10001 "
b10001 #
#126
b1100001000 !
b1100001000 $
b10010 "
b10010 #
#133
b1100011100 !
b1100011100 $
b10011 "
b10011 #
#140
b1100110000 !
b1100110000 $
b10100 "
b10100 #
#147
b1101000100 !
b1101000100 $
b10101 "
b10101 #
#154
b1101011000 !
b1101011000 $
b10110 "
b10110 #
#161
b1101101100 !
b1101101100 $
b10111 "
b10111 #
#168
b1110000000 !
b1110000000 $
b11000 "
b11000 #
#175
b1110010000 !
b1110010000 $
b11001 "
b11001 #
#182
b1110100000 !
b1110100000 $
b11010 "
b11010 #
#189
b1110110000 !
b1110110000 $
b11011 "
b11011 #
#196
b1111000000 !
b1111000000 $
b11100 "
b11100 #
#203
b1111010000 !
b1111010000 $
b11101 "
b11101 #
#210
b1111100000 !
b1111100000 $
b11110 "
b11110 #
#217
b1111110000 !
b1111110000 $
b11111 "
b11111 #
#224
b10000000000 !
b10000000000 $
b100000 "
b100000 #
#231
b10000010000 !
b10000010000 $
b100001 "
b100001 #
#238
b10000100000 !
b10000100000 $
b100010 "
b100010 #
#245
b10000110000 !
b10000110000 $
b100011 "
b100011 #
#252
b10001000000 !
b10001000000 $
b100100 "
b100100 #
#259
b10001010000 !
b10001010000 $
b100101 "
b100101 #
#266
b10001100000 !
b10001100000 $
b100110 "
b100110 #
#273
b10001110000 !
b10001110000 $
b100111 "
b100111 #
#280
b10010000000 !
b10010000000 $
b101000 "
b101000 #
#287
b10010001100 !
b10010001100 $
b101001 "
b101001 #
#294
b10010011000 !
b10010011000 $
b101010 "
b101010 #
#301
b10010100100 !
b10010100100 $
b101011 "
b101011 #
#308
b10010110000 !
b10010110000 $
b101100 "
b101100 #
#315
b10010111100 !
b10010111100 $
b101101 "
b101101 #
#322
b10011001000 !
b10011001000 $
b101110 "
b101110 #
#329
b10011010100 !
b10011010100 $
b101111 "
b101111 #
#336
b10011100000 !
b10011100000 $
b110000 "
b110000 #
#343
b10011101100 !
b10011101100 $
b110001 "
b110001 #
#350
b10011111000 !
b10011111000 $
b110010 "
b110010 #
#357
b10100000100 !
b10100000100 $
b110011 "
b110011 #
#364
b10100010000 !
b10100010000 $
b110100 "
b110100 #
#371
b10100011100 !
b10100011100 $
b110101 "
b110101 #
#378
b10100101000 !
b10100101000 $
b110110 "
b110110 #
#385
b10100110100 !
b10100110100 $
b110111 "
b110111 #
#392
b10101000000 !
b10101000000 $
b111000 "
b111000 #
#399
b10101001100 !
b10101001100 $
b111001 "
b111001 #
#406
b10101011000 !
b10101011000 $
b111010 "
b111010 #
#413
b10101100100 !
b10101100100 $
b111011 "
b111011 #
#420
b10101110000 !
b10101110000 $
b111100 "
b111100 #
#427
b10101111100 !
b10101111100 $
b111101 "
b111101 #
#434
b10110001000 !
b10110001000 $
b111110 "
b111110 #
#441
b10110010100 !
b10110010100 $
b111111 "
b111111 #
#448
b10110100000 !
b10110100000 $
b1000000 "
b1000000 #
#455
b10110101100 !
b10110101100 $
b1000001 "
b1000001 #
#462
b10110111000 !
b10110111000 $
b1000010 "
b1000010 #
#469
b10111000100 !
b10111000100 $
b1000011 "
b1000011 #
#476
b10111010000 !
b10111010000 $
b1000100 "
b1000100 #
#483
b10111011100 !
b10111011100 $
b1000101 "
b1000101 #
#490
b10111101000 !
b10111101000 $
b1000110 "
b1000110 #
#497
b10111110100 !
b10111110100 $
b1000111 "
b1000111 #
#504
b11000000000 !
b11000000000 $
b1001000 "
b1001000 #
#511
b11000001010 !
b11000001010 $
b1001001 "
b1001001 #
#518
b11000010100 !
b11000010100 $
b1001010 "
b1001010 #
#525
b11000011110 !
b11000011110 $
b1001011 "
b1001011 #
#532
b11000101000 !
b11000101000 $
b1001100 "
b1001100 #
#539
b11000110010 !
b11000110010 $
b1001101 "
b1001101 #
#546
b11000111100 !
b11000111100 $
b1001110 "
b1001110 #
#553
b11001000110 !
b11001000110 $
b1001111 "
b1001111 #
#560
b11001010000 !
b11001010000 $
b1010000 "
b1010000 #
#567
b11001011010 !
b11001011010 $
b1010001 "
b1010001 #
#574
b11001100100 !
b11001100100 $
b1010010 "
b1010010 #
#581
b11001101110 !
b11001101110 $
b1010011 "
b1010011 #
#588
b11001111000 !
b11001111000 $
b1010100 "
b1010100 #
#595
b11010000010 !
b11010000010 $
b1010101 "
b1010101 #
#602
b11010001100 !
b11010001100 $
b1010110 "
b1010110 #
#609
b11010010110 !
b11010010110 $
b1010111 "
b1010111 #
#616
b11010100000 !
b11010100000 $
b1011000 "
b1011000 #
#623
b11010101010 !
b11010101010 $
b1011001 "
b1011001 #
#630
b11010110100 !
b11010110100 $
b1011010 "
b1011010 #
#637
b11010111110 !
b11010111110 $
b1011011 "
b1011011 #
#644
b11011001000 !
b11011001000 $
b1011100 "
b1011100 #
#651
b11011010010 !
b11011010010 $
b1011101 "
b1011101 #
#658
b11011011100 !
b11011011100 $
b1011110 "
b1011110 #
#665
b11011100110 !
b11011100110 $
b1011111 "
b1011111 #
#672
b11011110000 !
b11011110000 $
b1100000 "
b1100000 #
