Level1/dev.v
module dev(
    input wire signed [19:0] SP_out, // Input from softplus module
    output reg signed [19:0] D_out // Output from dev module
);

    reg [19:0] epsilon;
    reg [39:0] temp_mult;

    reg [39:0] scaled_SP;
    reg [19:0] min, max, mid;
    reg [39:0] mid_squared;

    always @ (*)
    begin
        epsilon = $urandom_range(0, 32767); // Generate a random unsigned number from 0 to 32767 (2^15 - 1)

        if (SP_out[19] == 1)
            D_out = 20'd0; // Return 0 for negative input
        
        else
        begin
            scaled_SP = SP_out << 15; // Shift left by 15 bits to create input with 30 fraction bits instead of 15

            min = 0;
            max = 20'shFFFFF; // Initialize max based on scaled value

            while (min < max)
            begin
                mid = (min + max) >> 1; // Average between min and max
                mid_squared = mid * mid;

                if (mid_squared == scaled_SP)
                begin
                    min = mid;
                    max = mid;
                end

                else if (mid_squared < scaled_SP)
                    min = mid + 1;
                
                else
                    max = mid - 1;
            end

            temp_mult = (min * epsilon) >>> 15;
            D_out = temp_mult[19:0];
        end
    end

endmodule

Level1/dev_tb.v
`include "dev.v"

module dev_tb;

    reg signed [19:0] INPUT;

    wire signed [19:0] OUTPUT;

    dev dev1(
        .SP_out(INPUT),
        
        .D_out(OUTPUT)
    );
    
    initial begin
        $dumpfile("dev_tb.vcd");
        $dumpvars(0, dev_tb);

        INPUT = 20'shF8000;

        #7;

        repeat(72)
        begin
            INPUT += 20'sh1000;
            #7;
        end
    end

endmodule

Level1/dev_tb.vcd
$date
	Sun Dec 08 22:42:47 2024
$end
$version
	Icarus Verilog
$end
$timescale
	1s
$end
$scope module dev_tb $end
$var wire 20 ! OUTPUT [19:0] $end
$var reg 20 " INPUT [19:0] $end
$scope module dev1 $end
$var wire 20 # SP_out [19:0] $end
$var reg 20 $ D_out [19:0] $end
$var reg 20 % epsilon [19:0] $end
$var reg 20 & max [19:0] $end
$var reg 20 ' mid [19:0] $end
$var reg 40 ( mid_squared [39:0] $end
$var reg 20 ) min [19:0] $end
$var reg 40 * scaled_SP [39:0] $end
$var reg 40 + temp_mult [39:0] $end
$upscope $end
$upscope $end
$enddefinitions $end
$comment Show the parameter values. $end
$dumpall
$end
#0
$dumpvars
bx +
bx *
bx )
bx (
bx '
bx &
b100100100001010 %
b0 $
b11111000000000000000 #
b11111000000000000000 "
b0 !
$end
#7
b10000001000100 %
b11111001000000000000 "
b11111001000000000000 #
#14
b1001000010 %
b11111010000000000000 "
b11111010000000000000 #
#21
b1100011111000 %
b11111011000000000000 "
b11111011000000000000 #
#28
b100001101011100 %
b11111100000000000000 "
b11111100000000000000 #
#35
b110001101101111 %
b11111101000000000000 "
b11111101000000000000 #
#42
b1100101100001 %
b11111110000000000000 "
b11111110000000000000 #
#49
b10010011011 %
b11111111000000000000 "
b11111111000000000000 #
#56
b0 +
b1 (
b1 '
b0 &
b0 )
b0 *
b100000001111001 %
b0 "
b0 #
#63
b1011111010110 !
b1011111010110 $
b1011111010110 +
b10110101000010 )
b111111111111110101010000001 (
b10110101000001 '
b10110101000010 &
b1000000000000000000000000000 *
b100001101101011 %
b1000000000000 "
b1000000000000 #
#70
b10111011001000 !
b10111011001000 $
b10111011001000 +
b10000000000001000000000000001 (
b100000000000001 '
b100000000000000 &
b100000000000000 )
b10000000000000000000000000000 *
b101110110010001 %
b10000000000000 "
b10000000000000 #
#77
b11000010001011 !
b11000010001011 $
b11000010001011 +
b10111111111110100000011000001 (
b100111001100001 '
b100111001100010 &
b100111001100010 )
b11000000000000000000000000000 *
b100111101000110 %
b11000000000000 "
b11000000000000 #
#84
b101011101000011 !
b101011101000011 $
b101011101000011 +
b11111111111101111010100000001 (
b101101010000001 '
b101101010000010 &
b101101010000010 )
b100000000000000000000000000000 *
b111101101101010 %
b100000000000000 "
b100000000000000 #
#91
b100111001010110 !
b100111001010110 $
b100111001010110 +
b100111111111111011001101100001 (
b110010100110001 '
b110010100110010 &
b110010100110010 )
b101000000000000000000000000000 *
b110001100010110 %
b101000000000000 "
b101000000000000 #
#98
b110110110001011 !
b110110110001011 $
b110110110001011 +
b101111111111110011001111110001 (
b110111011011001 '
b110111011011010 &
b110111011011010 )
b110000000000000000000000000000 *
b111111001111110 %
b110000000000000 "
b110000000000000 #
#105
b10111001100110 !
b10111001100110 $
b10111001100110 +
b111000000000010100000110001001 (
b111011110111101 '
b111011110111100 &
b111011110111100 )
b111000000000000000000000000000 *
b11000110011011 %
b111000000000000 "
b111000000000000 #
#112
b11000101111011 !
b11000101111011 $
b11000101111011 +
b1000000000000010000000000000001 (
b1000000000000001 '
b1000000000000000 &
b1000000000000000 )
b1000000000000000000000000000000 *
b11000101111011 %
b1000000000000000 "
b1000000000000000 #
#119
b10110100011101 !
b10110100011101 $
b10110100011101 +
b1001000000000010101110110011001 (
b1000011111000101 '
b1000011111000100 &
b1000011111000100 )
b1001000000000000000000000000000 *
b10101010001001 %
b1001000000000000 "
b1001000000000000 #
#126
b1000011110101001 !
b1000011110101001 $
b1000011110101001 +
b1010000000000010110100101001001 (
b1000111100011101 '
b1000111100011100 &
b1000111100011100 )
b1010000000000000000000000000000 *
b111100101010111 %
b1010000000000000 "
b1010000000000000 #
#133
b10001100010010 !
b10001100010010 $
b10001100010010 +
b1011000000000010100111001110001 (
b1001011000011001 '
b1001011000011000 &
b1001011000011000 )
b1011000000000000000000000000000 *
b1110111101001 %
b1011000000000000 "
b1011000000000000 #
#140
b10110100001 !
b10110100001 $
b10110100001 +
b1100000000000001010111110011001 (
b1001110011000101 '
b1001110011000100 &
b1001110011000100 )
b1100000000000000000000000000000 *
b10010011001 %
b1100000000000000 "
b1100000000000000 #
#147
b111111101101101 !
b111111101101101 $
b111111101101101 +
b1101000000000100101010111101001 (
b1010001100101101 '
b1010001100101100 &
b1010001100101100 )
b1101000000000000000000000000000 *
b110001111110110 %
b1101000000000000 "
b1101000000000000 #
#154
b1010010011010010 !
b1010010011010010 $
b1010010011010010 +
b1110000000000010101011000111001 (
b1010100101010101 '
b1010100101010100 &
b1010100101010100 )
b1110000000000000000000000000000 *
b111110010011000 %
b1110000000000000 "
b1110000000000000 #
#161
b100011011010101 !
b100011011010101 $
b100011011010101 +
b1110111111111110110100010011001 (
b1010111101000101 '
b1010111101000110 &
b1010111101000110 )
b1111000000000000000000000000000 *
b11001110111011 %
b1111000000000000 "
b1111000000000000 #
#168
b101001000000101 !
b101001000000101 $
b101001000000101 +
b10000000000000000001001000011001 (
b1011010100000101 '
b1011010100000100 &
b1011010100000100 )
b10000000000000000000000000000000 *
b11101000000000 %
b10000000000000000 "
b10000000000000000 #
#175
b100100000000001 !
b100100000000001 $
b100100000000001 +
b10001000000000101010111101110001 (
b1011101010011001 '
b1011101010011000 &
b1011101010011000 )
b10001000000000000000000000000000 *
b11000101100101 %
b10001000000000000 "
b10001000000000000 #
#182
b1000001011000010 !
b1000001011000010 $
b1000001011000010 +
b10010000000000011000000000000001 (
b1100000000000001 '
b1100000000000000 &
b1100000000000000 )
b10010000000000000000000000000000 *
b101011100101100 %
b10010000000000000 "
b10010000000000000 #
#189
b100100011011011 !
b100100011011011 $
b100100011011011 +
b10010111111111010001101010000001 (
b1100010101000001 '
b1100010101000010 &
b1100010101000010 )
b10011000000000000000000000000000 *
b10111101000111 %
b10011000000000000 "
b10011000000000000 #
#196
b1000111101010 !
b1000111101010 $
b1000111101010 +
b10011111111111010011100011000001 (
b1100101001100001 '
b1100101001100010 &
b1100101001100010 )
b10100000000000000000000000000000 *
b101101010101 %
b10100000000000000 "
b10100000000000000 #
#203
b10100100000111 !
b10100100000111 $
b10100100000111 +
b10100111111111100000001011000001 (
b1100111101100001 '
b1100111101100010 &
b1100111101100010 )
b10101000000000000000000000000000 *
b1100101010011 %
b10101000000000000 "
b10101000000000000 #
#210
b10100101100110 !
b10100101100110 $
b10100101100110 +
b10110000000000100101101010011001 (
b1101010001000101 '
b1101010001000100 &
b1101010001000100 )
b10110000000000000000000000000000 *
b1100011110111 %
b10110000000000000 "
b10110000000000000 #
#217
b111000100100001 !
b111000100100001 $
b111000100100001 +
b10111000000000000100001001010001 (
b1101100100001001 '
b1101100100001000 &
b1101100100001000 )
b10111000000000000000000000000000 *
b100001010111001 %
b10111000000000000 "
b10111000000000000 #
#224
b11011110011111 !
b11011110011111 $
b11011110011111 +
b11000000000000100000000111111001 (
b1101110110110101 '
b1101110110110100 &
b1101110110110100 )
b11000000000000000000000000000000 *
b10000000011101 %
b11000000000000000 "
b11000000000000000 #
#231
b111111110011111 !
b111111110011111 $
b111111110011111 +
b11000111111111011110011010011001 (
b1110001001000101 '
b1110001001000110 &
b1110001001000110 )
b11001000000000000000000000000000 *
b100100000110010 %
b11001000000000000 "
b11001000000000000 #
#238
b1100000001101011 !
b1100000001101011 $
b1100000001101011 +
b11001111111111110101110110000001 (
b1110011011000001 '
b1110011011000010 &
b1110011011000010 )
b11010000000000000000000000000000 *
b110101010111100 %
b11010000000000000 "
b11010000000000000 #
#245
b100100001100000 !
b100100001100000 $
b100100001100000 +
b11010111111111001111001101011001 (
b1110101100100101 '
b1110101100100110 &
b1110101100100110 )
b11011000000000000000000000000000 *
b10011101100110 %
b11011000000000000 "
b11011000000000000 #
#252
b100011001000110 !
b100011001000110 $
b100011001000110 +
b11100000000000110010011100110001 (
b1110111101111001 '
b1110111101111000 &
b1110111101111000 )
b11100000000000000000000000000000 *
b10010110010000 %
b11100000000000000 "
b11100000000000000 #
#259
b100100001101 !
b100100001101 $
b100100001101 +
b11101000000000010001110111111001 (
b1111001110110101 '
b1111001110110100 &
b1111001110110100 )
b11101000000000000000000000000000 *
b10011000001 %
b11101000000000000 "
b11101000000000000 #
#266
b11010000101 !
b11010000101 $
b11010000101 +
b11101111111111000011010011001001 (
b1111011111011101 '
b1111011111011110 &
b1111011111011110 )
b11110000000000000000000000000000 *
b1101011110 %
b11110000000000000 "
b11110000000000000 #
#273
b10100011111110 !
b10100011111110 $
b10100011111110 +
b11111000000000100011100000110001 (
b1111101111111001 '
b1111101111111000 &
b1111101111111000 )
b11111000000000000000000000000000 *
b1010011010011 %
b11111000000000000 "
b11111000000000000 #
#280
b1011010110011110 !
b1011010110011110 $
b1011010110011110 +
b100000000000000100000000000000001 (
b10000000000000001 '
b10000000000000000 &
b10000000000000000 )
b100000000000000000000000000000000 *
b101101011001111 %
b100000000000000000 "
b100000000000000000 #
#287
b110110001001101 !
b110110001001101 $
b110110001001101 +
b100001000000000011100100000110001 (
b10000001111111001 '
b10000001111111000 &
b10000001111111000 )
b100001000000000000000000000000000 *
b11010101010011 %
b100001000000000000 "
b100001000000000000 #
#294
b100011110 !
b100011110 $
b100011110 +
b100010000000000000001001111000001 (
b10000011111100001 '
b10000011111100000 &
b10000011111100000 )
b100010000000000000000000000000000 *
b10001011 %
b100010000000000000 "
b100010000000000000 #
#301
b101101101010110 !
b101101101010110 $
b101101101010110 +
b100011000000000111100100110001001 (
b10000101110111101 '
b10000101110111100 &
b10000101110111100 )
b100011000000000000000000000000000 *
b10101110101011 %
b100011000000000000 "
b100011000000000000 #
#308
b1001011110101010 !
b1001011110101010 $
b1001011110101010 +
b100100000000000110101011101010001 (
b10000111110001001 '
b10000111110001000 &
b10000111110001000 )
b100100000000000000000000000000000 *
b100011101111111 %
b100100000000000000 "
b100100000000000000 #
#315
b110111110010011 !
b110111110010011 $
b110111110010011 +
b100100111111111010101000010011001 (
b10001001101000101 '
b10001001101000110 &
b10001001101000110 )
b100101000000000000000000000000000 *
b11001111100010 %
b100101000000000000 "
b100101000000000000 #
#322
b1001111010010010 !
b1001111010010010 $
b1001111010010010 +
b100110000000000011011111000110001 (
b10001011011111001 '
b10001011011111000 &
b10001011011111000 )
b100110000000000000000000000000000 *
b100100011000010 %
b100110000000000000 "
b100110000000000000 #
#329
b1001001011011100 !
b1001001011011100 $
b1001001011011100 +
b100110111111111100100010001001001 (
b10001101010011101 '
b10001101010011110 &
b10001101010011110 )
b100111000000000000000000000000000 *
b100001010000100 %
b100111000000000000 "
b100111000000000000 #
#336
b111000101101011 !
b111000101101011 $
b111000101101011 +
b101000000000000110110100010110001 (
b10001111000111001 '
b10001111000111000 &
b10001111000111000 )
b101000000000000000000000000000000 *
b11001010111001 %
b101000000000000000 "
b101000000000000000 #
#343
b10001000101011 !
b10001000101011 $
b10001000101011 +
b101000111111111100110000110011001 (
b10010000111000101 '
b10010000111000110 &
b10010000111000110 )
b101001000000000000000000000000000 *
b111100011000 %
b101001000000000000 "
b101001000000000000 #
#350
b10001110110111010 !
b10001110110111010 $
b10001110110111010 +
b101010000000000000010111011010001 (
b10010010101001001 '
b10010010101001000 &
b10010010101001000 )
b101010000000000000000000000000000 *
b111110010110100 %
b101010000000000000 "
b101010000000000000 #
#357
b1110010010010010 !
b1110010010010010 $
b1110010010010010 +
b101010111111111101110000110000001 (
b10010100011000001 '
b10010100011000010 &
b10010100011000010 )
b101011000000000000000000000000000 *
b110001010010111 %
b101011000000000000 "
b101011000000000000 #
#364
b1011110010000011 !
b1011110010000011 $
b1011110010000011 +
b101100000000000101110000101100001 (
b10010110000110001 '
b10010110000110000 &
b10010110000110000 )
b101100000000000000000000000000000 *
b101000001100010 %
b101100000000000000 "
b101100000000000000 #
#371
b1000000001101010 !
b1000000001101010 $
b1000000001101010 +
b101101000000000100000110010111001 (
b10010111110010101 '
b10010111110010100 &
b10010111110010100 )
b101101000000000000000000000000000 *
b11011000100101 %
b101101000000000000 "
b101101000000000000 #
#378
b1110000110001101 !
b1110000110001101 $
b1110000110001101 +
b101101111111110110110111101101001 (
b10011001011101101 '
b10011001011101110 &
b10011001011101110 )
b101110000000000000000000000000000 *
b101111000010000 %
b101110000000000000 "
b101110000000000000 #
#385
b101001100010000 !
b101001100010000 $
b101001100010000 +
b101111000000000010111110010000001 (
b10011011001000001 '
b10011011001000000 &
b10011011001000000 )
b101111000000000000000000000000000 *
b10001001000101 %
b101111000000000000 "
b101111000000000000 #
#392
b10010110011111111 !
b10010110011111111 $
b10010110011111111 +
b110000000000000000100101101010001 (
b10011100110001001 '
b10011100110001000 &
b10011100110001000 )
b110000000000000000000000000000000 *
b111101011100010 %
b110000000000000000 "
b110000000000000000 #
#399
b10000111100000001 !
b10000111100000001 $
b10000111100000001 +
b110001000000000001101010111010001 (
b10011110011001001 '
b10011110011001000 &
b10011110011001000 )
b110001000000000000000000000000000 *
b110110110000001 %
b110001000000000000 "
b110001000000000000 #
#406
b10001110000011100 !
b10001110000011100 $
b10001110000011100 +
b110010000000000101000000000000001 (
b10100000000000001 '
b10100000000000000 &
b10100000000000000 )
b110010000000000000000000000000000 *
b111000110100101 %
b110010000000000000 "
b110010000000000000 #
#413
b10000111110000110 !
b10000111110000110 $
b10000111110000110 +
b110011000000001001010111101100001 (
b10100001100110001 '
b10100001100110000 &
b10100001100110000 )
b110011000000000000000000000000000 *
b110101110001010 %
b110011000000000000 "
b110011000000000000 #
#420
b111100001100111 !
b111100001100111 $
b111100001100111 +
b110011111111111001001100000111001 (
b10100011001010101 '
b10100011001010110 &
b10100011001010110 )
b110100000000000000000000000000000 *
b10111100111010 %
b110100000000000000 "
b110100000000000000 #
#427
b1011111111010011 !
b1011111111010011 $
b1011111111010011 +
b110100111111111011110111101111001 (
b10100100101110101 '
b10100100101110110 &
b10100100101110110 )
b110101000000000000000000000000000 *
b100101010000111 %
b110101000000000000 "
b110101000000000000 #
#434
b11110010100 !
b11110010100 $
b11110010100 +
b110101111111111100000010110101001 (
b10100110010001101 '
b10100110010001110 &
b10100110010001110 )
b110110000000000000000000000000000 *
b1011101011 %
b110110000000000000 "
b110110000000000000 #
#441
b100101000101111 !
b100101000101111 $
b100101000101111 +
b110110111111111000100011001001001 (
b10100111110011101 '
b10100111110011110 &
b10100111110011110 )
b110111000000000000000000000000000 *
b1110001001011 %
b110111000000000000 "
b110111000000000000 #
#448
b10000000111100011 !
b10000000111100011 $
b10000000111100011 +
b111000000000000101011001110010001 (
b10101001010101001 '
b10101001010101000 &
b10101001010101000 )
b111000000000000000000000000000000 *
b110000101111001 %
b111000000000000000 "
b111000000000000000 #
#455
b1110000000100100 !
b1110000000100100 $
b1110000000100100 +
b111000111111110111010100110010001 (
b10101010110101001 '
b10101010110101010 &
b10101010110101010 )
b111001000000000000000000000000000 *
b101001111111001 %
b111001000000000000 "
b111001000000000000 #
#462
b10100000011101 !
b10100000011101 $
b10100000011101 +
b111001111111110111101101001011001 (
b10101100010100101 '
b10101100010100110 &
b10101100010100110 )
b111010000000000000000000000000000 *
b111011100110 %
b111010000000000000 "
b111010000000000000 #
#469
b1101010100110110 !
b1101010100110110 $
b1101010100110110 +
b111011000000000101111111001001001 (
b10101101110011101 '
b10101101110011100 &
b10101101110011100 )
b111011000000000000000000000000000 *
b100111010000011 %
b111011000000000000 "
b111011000000000000 #
#476
b101011001110010 !
b101011001110010 $
b101011001110010 +
b111011111111110101110010101010001 (
b10101111010001001 '
b10101111010001010 &
b10101111010001010 )
b111100000000000000000000000000000 *
b1111110010001 %
b111100000000000000 "
b111100000000000000 #
#483
b1011111101110011 !
b1011111101110011 $
b1011111101110011 +
b111101000000000111101111101111001 (
b10110000101110101 '
b10110000101110100 &
b10110000101110100 )
b111101000000000000000000000000000 *
b100010101010101 %
b111101000000000000 "
b111101000000000000 #
#490
b10101101001011111 !
b10101101001011111 $
b10101101001011111 +
b111101111111111001000010000111001 (
b10110010001010101 '
b10110010001010110 &
b10110010001010110 )
b111110000000000000000000000000000 *
b111110001101100 %
b111110000000000000 "
b111110000000000000 #
#497
b10100101111111100 !
b10100101111111100 $
b10100101111111100 +
b111110111111110100111011101100001 (
b10110011100110001 '
b10110011100110010 &
b10110011100110010 )
b111111000000000000000000000000000 *
b111011001001110 %
b111111000000000000 "
b111111000000000000 #
#504
b1111101010000000 !
b1111101010000000 $
b1111101010000000 +
b111111111111111010111010001010001 (
b10110101000001001 '
b10110101000001010 &
b10110101000001010 )
b1000000000000000000000000000000000 *
b101100010010001 %
b1000000000000000000 "
b1000000000000000000 #
