Level1/epsilon.v
module epsilon(
    input wire clk,                   // Global clock
    input wire reset,                 // Reset signal to initialize epsilon
    input wire signed [19:0] D_out,   // Input from dev module

    output wire signed [19:0] E_out   // Output from epsilon module
);

    reg signed [19:0] epsilon; // Pseudorandomly-generated number
    wire feedback;

    assign feedback = epsilon[14] ^ !epsilon[9] ^ epsilon[5] ^ !epsilon[2] ^ epsilon[0] ^ !D_out[1] ^ D_out[4] ^ !D_out[8] ^ D_out[13];

    always @ (posedge clk or posedge reset)
    begin
        if (reset)
            epsilon <= 20'sh02E92; // Non-zero initial state for epsilon
        else
            epsilon <= {5'b0, epsilon[4:0], ~epsilon[14:13], feedback, ~epsilon[12:8], epsilon[6:5]};
    end

    wire signed [39:0] temp_mult;

    assign temp_mult = (D_out * epsilon) >>> 15;
    assign E_out = temp_mult[19:0];

endmodule

Level1/epsilon_tb.v
`include "epsilon.v"

module epsilon_tb;

    reg CLOCK, RESET;
    reg signed [19:0] INPUT;

    wire signed [19:0] OUTPUT;

    epsilon G0(
        .clk(CLOCK),
        .reset(RESET),
        .D_out(INPUT),

        .E_out(OUTPUT)
    );

    initial begin
        $dumpfile("epsilon_tb.vcd");
        $dumpvars(0, epsilon_tb);

        CLOCK = 1;
        RESET = 1;

        INPUT = $urandom_range(0, 524287);

        #7;

        CLOCK = !CLOCK;

        #7;

        CLOCK = !CLOCK;
        RESET = 0;
        
        INPUT = $urandom_range(0, 524287);

        #7;

        repeat(1000)
        begin
            CLOCK = !CLOCK;

            #7;

            CLOCK = !CLOCK;
            
            INPUT = $urandom_range(0, 524287);

            #7;
        end
    end

endmodule

Level1/epsilon_tb.vcd
$date
	Wed Dec 11 12:12:41 2024
$end
$version
	Icarus Verilog
$end
$timescale
	1s
$end
$scope module epsilon_tb $end
$var wire 20 ! OUTPUT [19:0] $end
$var reg 1 " CLOCK $end
$var reg 20 # INPUT [19:0] $end
$var reg 1 $ RESET $end
$scope module G0 $end
$var wire 20 % D_out [19:0] $end
$var wire 1 " clk $end
$var wire 1 & feedback $end
$var wire 1 $ reset $end
$var wire 40 ' temp_mult [39:0] $end
$var wire 20 ( E_out [19:0] $end
$var reg 20 ) epsilon [19:0] $end
$upscope $end
$upscope $end
$enddefinitions $end
$comment Show the parameter values. $end
$dumpall
$end
#0
$dumpvars
b10111010010010 )
b11010100100110001 (
b11010100100110001 '
1&
b1001001000010101001 %
1$
b1001001000010101001 #
1"
b11010100100110001 !
$end
#7
0"
#14
b100101011000100 )
0&
b10010110110010001 !
b10010110110010001 (
b10010110110010001 '
b100000010001001010 #
b100000010001001010 %
0$
1"
#21
0"
#28
b1000101010110 )
1&
b10011100101 !
b10011100101 (
b10011100101 '
b10010000100110 #
b10010000100110 %
1"
#35
0"
#42
b101101110111010 )
1&
b10001111001001010 !
b10001111001001010 (
b10001111001001010 '
b11000111110000010 #
b11000111110000010 %
1"
#49
0"
#56
b110100110010001 )
1&
b110111100011100101 !
b110111100011100101 (
b110111100011100101 '
b1000011010111001011 #
b1000011010111001011 %
1"
#63
0"
#70
b100010011011000 )
1&
b110101011110110010 !
b110101011110110010 (
b110101011110110010 '
b1100011011011111100 #
b1100011011011111100 %
1"
#77
0"
#84
b110000111101110 )
0&
b10011011010101110 !
b10011011010101110 (
b10011011010101110 '
b11001011000010100 #
b11001011000010100 %
1"
#91
0"
#98
b11100001111011 )
1&
b10000010001000 !
b10000010001000 (
b10000010001000 '
b100100110111010 #
b100100110111010 %
1"
#105
0"
#112
1&
b110111010011111 )
b110111101110001110 !
b110111101110001110 (
b110111101110001110 '
b1000000011110011111 #
b1000000011110011111 %
1"
#119
0"
#126
b111110011000100 )
1&
b1000001101101111011 !
b1000001101101111011 (
b1000001101101111011 '
b1000011011010111110 #
b1000011011010111110 %
1"
#133
0"
#140
b1000010001110 )
0&
b1100000110100000 !
b1100000110100000 (
b1100000110100000 '
b1011101100100011111 #
b1011101100100011111 %
1"
#147
0"
#154
b11101100111100 )
1&
b100100101011111101 !
b100100101011111101 (
b100100101011111101 '
b1001111010001101110 #
b1001111010001101110 %
1"
#161
0"
#168
1&
b111001010010001 )
b1101110011101100101 !
b1101110011101100101 (
b1101110011101100101 '
b1111011011010100010 #
b1111011011010100010 %
1"
#175
0"
#182
b100010010110100 )
0&
b110101001011111000 !
b110101001011111000 (
b110101001011111000 '
b1100011000101101111 #
b1100011000101101111 %
1"
#189
0"
#196
1&
b101000101101101 )
b1010000011110000000 !
b1010000011110000000 (
b1010000011110000000 '
b1111110011111101111 #
b1111110011111101111 %
1"
#203
0"
#210
b11010110111011 )
0&
b10100110100101110 !
b10100110100101110 (
b10100110100101110 '
b110001100110111001 #
b110001100110111001 %
1"
#217
0"
#224
b110111000101001 )
b101010100101100011 !
b101010100101100011 (
b101010100101100011 '
b110001011110111100 #
b110001011110111100 %
1"
#231
0"
#238
b10010001000101 )
1&
b1100000011011011 !
b1100000011011011 (
b1100000011011011 '
b101010100010011110 #
b101010100010011110 %
1"
#245
0"
#252
b1011011101110 )
0&
b10101101111001011 !
b10101101111001011 (
b10101101111001011 '
b1111001010101111111 #
b1111001010101111111 %
1"
#259
0"
#266
b11101100100111 )
0&
b1101110100101001 !
b1101110100101001 (
b1101110100101001 '
b11101111010010011 #
b11101111010010011 %
1"
#273
0"
#280
b1111000010001 )
1&
b1000101001000 !
b1000101001000 (
b1000101001000 '
b100100110010110 #
b100100110010110 %
1"
#287
0"
#294
b100011110000100 )
0&
b110111110110011011 !
b110111110110011011 (
b110111110110011011 '
b1100011111101100110 #
b1100011111101100110 %
1"
#301
0"
#308
b1000101100000 )
1&
b10000111010011010 !
b10000111010011010 (
b10000111010011010 '
b1111100100110000011 #
b1111100100110000011 %
1"
#315
0"
#322
b1110111011 )
0&
b1100000011111 !
b1100000011111 (
b1100000011111 '
b110011101110110100 #
b110011101110110100 %
1"
#329
0"
#336
b110111101110001 )
0&
b110010011111110101 !
b110010011111110101 (
b110010011111110101 '
b111010000000000011 #
b111010000000000011 %
1"
#343
0"
#350
b100010001000011 )
0&
b11010010101111001 !
b11010010101111001 (
b11010010101111001 '
b110001011001010010 #
b110001011001010010 %
1"
#357
0"
#364
b110101101110 )
0&
b1001001001010110 !
b1001001001010110 (
b1001001001010110 '
b1010111001011000010 #
b1010111001011000010 %
1"
#371
0"
#378
b11101101001011 )
0&
b10101111001100111 !
b10101111001100111 (
b10101111001100111 '
b101111010001110001 #
b101111010001110001 %
1"
#385
0"
#392
b10111000010010 )
1&
b100000101000101 !
b100000101000101 (
b100000101000101 '
b1011010101011010 #
b1011010101011010 %
1"
#399
0"
#406
b100101011000100 )
1&
b1110110010110001 !
b1110110010110001 (
b1110110010110001 '
b11001010100111001 #
b11001010100111001 %
1"
#413
0"
#420
b1000111010110 )
0&
b11011110101010 !
b11011110101010 (
b11011110101010 '
b11000111101111011 #
b11000111101111011 %
1"
#427
0"
#434
b101101100111010 )
0&
b101111100011100100 !
b101111100011100100 (
b101111100011100100 '
b1000010101110011100 #
b1000010101110011100 %
1"
#441
0"
#448
b110100100010001 )
0&
b11010010111001000 !
b11010010111001000 (
b11010010111001000 '
b100000000111011001 #
b100000000111011001 %
1"
#455
0"
#462
b100010001011000 )
0&
b100110100011000011 !
b100110100011000011 (
b100110100011000011 '
b1001000001100100001 #
b1001000001100100001 %
1"
#469
0"
#476
b110000101101110 )
0&
b1010001001111100100 !
b1010001001111100100 (
b1010001001111100100 '
b1101010101111000010 #
b1101010101111000010 %
1"
#483
0"
#490
b11100001111011 )
0&
b10001011000101010 !
b10001011000101010 (
b10001011000101010 '
b100111011001100110 #
b100111011001100110 %
1"
#497
0"
#504
b110111000011111 )
1&
b100000010100001110 !
b100000010100001110 (
b100000010100001110 '
b100101100100000001 #
b100101100100000001 %
1"
#511
0"
#518
b111110011000100 )
1&
b100101000110000 !
b100101000110000 (
b100101000110000 '
b100110000011101 #
b100110000011101 %
1"
#525
0"
#532
b1000010001110 )
1&
b11011110111 !
b11011110111 (
b11011110111 '
b11010111100001 #
b11010111100001 %
1"
#539
0"
#546
b11101110111100 )
0&
b1001101110000100 !
b1001101110000100 (
b1001101110000100 '
b10100110100111110 #
b10100110100111110 %
1"
#553
0"
#560
b111001000010001 )
0&
b1010000111011010011 !
b1010000111011010011 (
b1010000111011010011 '
b1011010110011111110 #
b1011010110011111110 %
1"
#567
0"
#574
b100010000110100 )
1&
b11100011010011100 !
b11100011010011100 (
b11100011010011100 '
b110101010100110001 #
b110101010100110001 %
1"
#581
0"
#588
b101000111101101 )
0&
b10110010101 !
b10110010101 (
b10110010101 '
b100010111010 #
b100010111010 %
1"
#595
0"
#602
b11010100111011 )
0&
b10010001010001111 !
b10010001010001111 (
b10010001010001111 '
b101011101010110001 #
b101011101010110001 %
1"
#609
0"
#616
b110111000101001 )
0&
b111101100010001101 !
b111101100010001101 (
b111101100010001101 '
b1000111011111111111 #
b1000111011111111111 %
1"
#623
0"
#630
b10010001000101 )
0&
b1110101100111011 !
b1110101100111011 (
b1110101100111011 '
b110011111000101011 #
b110011111000101011 %
1"
#637
0"
#644
b1011001101110 )
0&
b1100101111111110 !
b1100101111111110 (
b1100101111111110 '
b1001000110000100010 #
b1001000110000100010 %
1"
#651
0"
#658
b11101100100111 )
0&
b11110101111010110 !
b11110101111010110 (
b11110101111010110 '
b1000010100001001011 #
b1000010100001001011 %
1"
#665
0"
#672
b1111000010001 )
1&
b1011111010100011 !
b1011111010100011 (
b1011111010100011 '
b110010101110011000 #
b110010101110011000 %
1"
#679
0"
#686
b100011110000100 )
0&
b1000011011110011 !
b1000011011110011 (
b1000011011110011 '
b1111000110001010 #
b1111000110001010 %
1"
#693
0"
#700
b1000101100000 )
0&
b10000111011010111 !
b10000111011010111 (
b10000111011010111 '
b1111100101101000101 #
b1111100101101000101 %
1"
#707
0"
#714
b1100111011 )
1&
b10011111001111 !
b10011111001111 (
b10011111001111 '
b1100010100101110011 #
b1100010100101110011 %
1"
#721
0"
#728
b110111111110001 )
0&
b1000110010011001001 !
b1000110010011001001 (
b1000110010011001001 '
b1010000011000100101 #
b1010000011000100101 %
1"
#735
0"
#742
b100010001000011 )
0&
b11100111000000100 !
b11100111000000100 (
b11100111000000100 '
b110110001001011001 #
b110110001001011001 %
1"
#749
0"
#756
b110101101110 )
1&
b1001110111101000 !
b1001110111101000 (
b1001110111101000 '
b1011110000100000111 #
b1011110000100000111 %
1"
#763
0"
#770
b11101111001011 )
0&
b10000000000100010 !
b10000000000100010 (
b10000000000100010 '
b100010010001010000 #
b100010010001010000 %
1"
#777
0"
#784
b10111000010010 )
0&
b101100001110101010 !
b101100001110101010 (
b101100001110101010 '
b1111010111000101000 #
b1111010111000101000 %
1"
#791
0"
#798
b100101001000100 )
1&
b111111100010001101 !
b111111100010001101 (
b111111100010001101 '
b1101101100000010011 #
b1101101100000010011 %
1"
#805
0"
#812
b1000111010110 )
b1111110101100000 !
b1111110101100000 (
b1111110101100000 '
b1110001101001011111 #
b1110001101001011111 %
1"
#819
0"
#826
b101101110111010 )
0&
b1001101000100001011 !
b1001101000100001011 (
b1001101000100001011 '
b1101011100010101000 #
b1101011100010101000 %
1"
#833
0"
#840
b110100100010001 )
0&
b100110110001000100 !
b100110110001000100 (
b100110110001000100 '
b101111001110101000 #
b101111001110101000 %
1"
#847
0"
#854
b100010001011000 )
0&
b100111110010110110 !
b100111110010110110 (
b100111110010110110 '
b1001010100001111110 #
b1001010100001111110 %
1"
#861
0"
#868
b110000101101110 )
1&
b10001110010010 !
b10001110010010 (
b10001110010010 '
b10111010111100 #
b10111010111100 %
1"
#875
0"
#882
b11100011111011 )
1&
b1100100110001010 !
b1100100110001010 (
b1100100110001010 '
b11100010010111101 #
b11100010010111101 %
1"
#889
0"
#896
b110111010011111 )
1&
b1010100001111010010 !
b1010100001111010010 (
b1010100001111010010 '
b1100001011110010010 #
b1100001011110010010 %
1"
#903
0"
#910
b111110011000100 )
0&
b1010001110110011110 !
b1010001110110011110 (
b1010001110110011110 '
b1010011111110010010 #
b1010011111110010010 %
1"
#917
0"
#924
b1000000001110 )
1&
b1110111100110 !
b1110111100110 (
b1110111100110 '
b1110111001100011 #
b1110111001100011 %
1"
#931
0"
#938
b11101110111100 )
1&
b100100101000111011 !
b100100101000111011 (
b100100101000111011 '
b1001110100000110001 #
b1001110100000110001 %
1"
#945
0"
#952
b111001010010001 )
0&
b11100010000010110 !
b11100010000010110 (
b11100010000010110 '
b11111100100011001 #
b11111100100011001 %
1"
#959
0"
#966
b100010000110100 )
0&
b100100111100010110 !
b100100111100010110 (
b100100111100010110 '
b1000101010101010010 #
b1000101010101010010 %
1"
#973
0"
#980
b101000101101101 )
0&
b1001111001001101100 !
b1001111001001101100 (
b1001111001001101100 '
b1111100011011001100 #
b1111100011011001100 %
1"
#987
0"
#994
b11010100111011 )
0&
b110001001100101110 !
b110001001100101110 (
b110001001100101110 '
b1110110010011100010 #
b1110110010011100010 %
1"
#1001
0"
#1008
b110111000101001 )
0&
b1001100001110010110 !
b1001100001110010110 (
b1001100001110010110 '
b1011000100100011000 #
b1011000100100011000 %
1"
#1015
0"
#1022
b10010001000101 )
1&
b10111100011000110 !
b10111100011000110 (
b10111100011000110 '
b1010011000110101111 #
b1010011000110101111 %
1"
#1029
0"
#1036
0&
b1011011101110 )
b10010100110001110 !
b10010100110001110 (
b10010100110001110 '
b1100111110100001010 #
b1100111110100001010 %
1"
#1043
0"
#1050
b11101100100111 )
0&
b101110001001100011 !
b101110001001100011 (
b101110001001100011 '
b1100011110111001101 #
b1100011110111001101 %
1"
#1057
0"
#1064
0&
b1111000010001 )
b11101101001011001 !
b11101101001011001 (
b11101101001011001 '
b1111110001101101101 #
b1111110001101101101 %
1"
#1071
0"
#1078
b100011100000100 )
0&
b11001011101110110 !
b11001011101110110 (
b11001011101110110 '
b101101111001101011 #
b101101111001101011 %
1"
#1085
0"
#1092
b1000101100000 )
1&
b101011010011111 !
b101011010011111 (
b101011010011111 '
b100111111000100010 #
b100111111000100010 %
1"
#1099
0"
#1106
b1110111011 )
1&
b101011010110 !
b101011010110 (
b101011010110 '
b10111001111101100 #
b10111001111101100 %
1"
#1113
0"
#1120
b110111111110001 )
1&
b10100000001100111 !
b10100000001100111 (
b10100000001100111 '
b10110111001011110 #
b10110111001011110 %
1"
#1127
0"
#1134
b100010011000011 )
0&
b110100111000001111 !
b110100111000001111 (
b110100111000001111 '
b1100010011011110001 #
b1100010011011110001 %
1"
#1141
0"
#1148
b110101101110 )
1&
b1111011001001 !
b1111011001001 (
b1111011001001 '
b10010010101110001 #
b10010010101110001 %
1"
#1155
0"
#1162
b11101111001011 )
0&
b11000010100101010 !
b11000010100101010 (
b11000010100101010 '
b110100000100011001 #
b110100000100011001 %
1"
#1169
0"
#1176
b10111000010010 )
0&
b10011011011110101 !
b10011011011110101 (
b10011011011110101 '
b110101111111110110 #
b110101111111110110 %
1"
#1183
0"
#1190
b100101001000100 )
1&
b1011110101001001 !
b1011110101001001 (
b1011110101001001 '
b10100011000111111 #
b10100011000111111 %
1"
#1197
0"
#1204
b1000111010110 )
0&
b1110001001110000 !
b1110001001110000 (
b1110001001110000 '
b1100101100100001001 #
b1100101100100001001 %
1"
#1211
0"
#1218
b101101100111010 )
1&
b101111110010101101 !
b101111110010101101 (
b101111110010101101 '
b1000011000011101011 #
b1000011000011101011 %
1"
#1225
0"
#1232
b110100110010001 )
0&
b101000000100100110 !
b101000000100100110 (
b101000000100100110 '
b110000100101100110 #
b110000100101100110 %
1"
#1239
0"
#1246
b100010001011000 )
0&
b111100111101011101 !
b111100111101011101 (
b111100111101011101 '
b1110010001010111111 #
b1110010001010111111 %
1"
#1253
0"
#1260
b110000101101110 )
1&
b10110101001011110 !
b10110101001011110 (
b10110101001011110 '
b11101110000010010 #
b11101110000010010 %
1"
#1267
0"
#1274
b11100011111011 )
0&
b100011011000001111 !
b100011011000001111 (
b100011011000001111 '
b1001111011110010111 #
b1001111011110010111 %
1"
#1281
0"
#1288
b110111000011111 )
1&
b111010111101000001 !
b111010111101000001 (
b111010111101000001 '
b1000100100001100110 #
b1000100100001100110 %
1"
#1295
0"
#1302
b111110011000100 )
1&
b11110101101101010 !
b11110101101101010 (
b11110101101101010 '
b11111100000101000 #
b11111100000101000 %
1"
#1309
0"
#1316
b1000010001110 )
1&
b1011110100111100 !
b1011110100111100 (
b1011110100111100 '
b1011011011100101100 #
b1011011011100101100 %
1"
#1323
0"
#1330
b11101110111100 )
1&
b100100100110010110 !
b100100100110010110 (
b100100100110010110 '
b1001110011011001111 #
b1001110011011001111 %
1"
#1337
0"
#1344
b111001010010001 )
1&
b1000000010111010011 !
b1000000010111010011 (
b1000000010111010011 '
b1000111111010010100 #
b1000111111010010100 %
1"
#1351
0"
#1358
b100010010110100 )
0&
b11100011011010010 !
b11100011011010010 (
b11100011011010010 '
b110100111101011111 #
b110100111101011111 %
1"
#1365
0"
#1372
b101000101101101 )
0&
b111101111110011010 !
b111101111110011010 (
b111101111110011010 '
b1100001011011001001 #
b1100001011011001001 %
1"
#1379
0"
#1386
b11010100111011 )
1&
b1100011111100001 !
b1100011111100001 (
b1100011111100001 '
b11110000010100100 #
b11110000010100100 %
1"
#1393
0"
#1400
b110111010101001 )
1&
b1001011001001101000 !
b1001011001001101000 (
b1001011001001101000 '
b1010110111011010010 #
b1010110111011010010 %
1"
#1407
0"
#1414
1&
b10010011000101 )
b10111101000100011 !
b10111101000100011 (
b10111101000100011 '
b1010010010001011010 #
b1010010010001011010 %
1"
#1421
0"
#1428
b1011011101110 )
0&
b10110111001000 !
b10110111001000 (
b10110111001000 '
b1111111110010101 #
b1111111110010101 %
1"
#1435
0"
#1442
b11101100100111 )
1&
b100010011100001001 !
b100010011100001001 (
b100010011100001001 '
b1001010100001100101 #
b1001010100001100101 %
1"
#1449
0"
#1456
b1111010010001 )
0&
b10100100010111111 !
b10100100010111111 (
b10100100010111111 '
b1010110000010101011 #
b1010110000010101011 %
1"
#1463
0"
#1470
b100011100000100 )
1&
b10010101001111000 !
b10010101001111000 (
b10010101001111000 '
b100001100111111001 #
b100001100111111001 %
1"
#1477
0"
#1484
b1000111100000 )
1&
b100111101101111 !
b100111101101111 (
b100111101101111 '
b100011100011010000 #
b100011100011010000 %
1"
#1491
0"
#1498
b1110111011 )
1&
b1001000111010 !
b1001000111010 (
b1001000111010 '
b100111000101111111 #
b100111000101111111 %
1"
#1505
0"
#1512
b110111111110001 )
0&
b1101110101110001001 !
b1101110101110001001 (
b1101110101110001001 '
b1111110100110101100 #
b1111110100110101100 %
1"
#1519
0"
#1526
b100010001000011 )
1&
b101001100100111 !
b101001100100111 (
b101001100100111 '
b1001101111101101 #
b1001101111101101 %
1"
#1533
0"
#1540
b110111101110 )
1&
b1010000110010010 !
b1010000110010010 (
b1010000110010010 '
b1011100110010110000 #
b1011100110010110000 %
1"
#1547
0"
#1554
1&
b11101111001011 )
b10011000010111101 !
b10011000010111101 (
b10011000010111101 '
b101000110001011101 #
b101000110001011101 %
1"
#1561
0"
#1568
b10111010010010 )
0&
b100010010110001 !
b100010010110001 (
b100010010110001 '
b1011110011001101 #
b1011110011001101 %
1"
#1575
0"
#1582
b100101001000100 )
0&
b11010000011101011 !
b11010000011101011 (
b11010000011101011 '
b101100111010010100 #
b101100111010010100 %
1"
#1589
0"
#1596
b1000101010110 )
1&
b11001111010110 !
b11001111010110 (
b11001111010110 '
b10111111011000010 #
b10111111011000010 %
1"
#1603
0"
#1610
b101101110111010 )
0&
b111010000110100110 !
b111010000110100110 (
b111010000110100110 '
b1010001000101001000 #
b1010001000101001000 %
1"
#1617
0"
#1624
b110100100010001 )
0&
b1100111011010011100 !
b1100111011010011100 (
b1100111011010011100 '
b1111101111111000111 #
b1111101111111000111 %
1"
#1631
0"
#1638
b100010001011000 )
1&
b11011001000000010 !
b11011001000000010 (
b11011001000000010 '
b110010110011011001 #
b110010110011011001 %
1"
#1645
0"
#1652
b110000111101110 )
1&
b101100000000010101 !
b101100000000010101 (
b101100000000010101 '
b111001100001001000 #
b111001100001001000 %
1"
#1659
0"
#1666
b11100011111011 )
1&
b100110100010101011 !
b100110100010101011 (
b100110100010101011 '
b1010110100101000110 #
b1010110100101000110 %
1"
#1673
0"
#1680
b110111010011111 )
1&
b1000000010011011011 !
b1000000010011011011 (
b1000000010011011011 '
b1001010011001111110 #
b1001010011001111110 %
1"
#1687
0"
#1694
1&
b111110011000100 )
b111001110000100010 !
b111001110000100010 (
b111001110000100010 '
b111011010000010111 #
b111011010000010111 %
1"
#1701
0"
#1708
0&
b1000010001110 )
b111000100011101 !
b111000100011101 (
b111000100011101 '
b110110101010011011 #
b110110101010011011 %
1"
#1715
0"
#1722
b11101100111100 )
0&
b1011101101101010 !
b1011101101101010 (
b1011101101101010 '
b11001010011111101 #
b11001010011111101 %
1"
#1729
0"
#1736
b111001000010001 )
1&
b101000010101111101 !
b101000010101111101 (
b101000010101111101 '
b101101010001010111 #
b101101010001010111 %
1"
#1743
0"
#1750
b100010010110100 )
0&
b11101111111010010 !
b11101111111010010 (
b11101111111010010 '
b110111110111110100 #
b110111110111110100 %
1"
#1757
0"
#1764
b101000101101101 )
0&
b111100000110001011 !
b111100000110001011 (
b111100000110001011 '
b1011110011110001000 #
b1011110011110001000 %
1"
#1771
0"
#1778
b11010100111011 )
0&
b100001101110011011 !
b100001101110011011 (
b100001101110011011 '
b1010001000110001111 #
b1010001000110001111 %
1"
#1785
0"
#1792
b110111000101001 )
1&
b101100111100101001 !
b101100111100101001 (
b101100111100101001 '
b110100001110100000 #
b110100001110100000 %
1"
#1799
0"
#1806
b10010011000101 )
1&
b10101011001111111 !
b10101011001111111 (
b10101011001111111 '
b1001010100001001000 #
b1001010100001001000 %
1"
#1813
0"
#1820
b1011011101110 )
0&
b10011001010100001 !
b10011001010100001 (
b10011001010100001 '
b1101010111110110101 #
b1101010111110110101 %
1"
#1827
0"
#1834
b11101100100111 )
0&
b11111010010110110 !
b11111010010110110 (
b11111010010110110 '
b1000011101101111110 #
b1000011101101111110 %
1"
#1841
0"
#1848
b1111000010001 )
1&
b11011111111101100 !
b11011111111101100 (
b11011111111101100 '
b1110111001011101101 #
b1110111001011101101 %
1"
#1855
0"
#1862
b100011110000100 )
1&
b10101100111010010 !
b10101100111010010 (
b10101100111010010 '
b100110101011110101 #
b100110101011110101 %
1"
#1869
0"
#1876
b1000111100000 )
0&
b1000110110111101 !
b1000110110111101 (
b1000110110111101 '
b111111011011111011 #
b111111011011111011 %
1"
#1883
0"
#1890
b1100111011 )
0&
b1001111000110 !
b1001111000110 (
b1001111000110 '
b110000111110001000 #
b110000111110001000 %
1"
#1897
0"
#1904
b110111101110001 )
0&
b1001010011101101111 !
b1001010011101101111 (
b1001010011101101111 '
b1010101100001110111 #
b1010101100001110111 %
1"
#1911
0"
#1918
b100010001000011 )
1&
b101100101010000011 !
b101100101010000011 (
b101100101010000011 '
b1010011101111001111 #
b1010011101111001111 %
1"
#1925
0"
#1932
b110111101110 )
1&
b10110100100011 !
b10110100100011 (
b10110100100011 '
b11001111011001011 #
b11001111011001011 %
1"
#1939
0"
#1946
b11101111001011 )
0&
b1001101100111 !
b1001101100111 (
b1001101100111 '
b10100110001001 #
b10100110001001 %
1"
#1953
0"
#1960
b10111000010010 )
1&
b100111011111010111 !
b100111011111010111 (
b100111011111010111 '
b1101101101101111101 #
b1101101101101111101 %
1"
#1967
0"
#1974
b100101011000100 )
1&
b1000001100011010 !
b1000001100011010 (
b1000001100011010 '
b1110000001110100 #
b1110000001110100 %
1"
#1981
0"
#1988
b1000111010110 )
0&
b1101001001111100 !
b1101001001111100 (
b1101001001111100 '
b1011110011010001100 #
b1011110011010001100 %
1"
#1995
0"
#2002
b101101100111010 )
1&
b100000110110000110 !
b100000110110000110 (
b100000110110000110 '
b101110000101011110 #
b101110000101011110 %
1"
#2009
0"
#2016
b110100110010001 )
1&
b1010011011111001000 !
b1010011011111001000 (
b1010011011111001000 '
b1100101001110100101 #
b1100101001110100101 %
1"
#2023
0"
#2030
b100010011011000 )
1&
b110110010000101110 !
b110110010000101110 (
b110110010000101110 '
b1100100111000110010 #
b1100100111000110010 %
1"
#2037
0"
#2044
b110000111101110 )
1&
b110111000000 !
b110111000000 (
b110111000000 '
b1000111111001 #
b1000111111001 %
1"
#2051
0"
#2058
b11100011111011 )
0&
b1001111101000000 !
b1001111101000000 (
b1001111101000000 '
b10110010110111110 #
b10110010110111110 %
1"
#2065
0"
#2072
b110111000011111 )
1&
b1100110010010100010 !
b1100110010010100010 (
b1100110010010100010 '
b1110110111001011011 #
b1110110111001011011 %
1"
#2079
0"
#2086
b111110011000100 )
1&
b10011000000000100 !
b10011000000000100 (
b10011000000000100 '
b10011011111100110 #
b10011011111100110 %
1"
#2093
0"
#2100
b1000010001110 )
1&
b1111010011100101 !
b1111010011100101 (
b1111010011100101 '
b1110110010110000101 #
b1110110010110000101 %
1"
#2107
0"
#2114
1&
b11101110111100 )
b1100101111111111 !
b1100101111111111 (
b1100101111111111 '
b11011010100100001 #
b11011010100100001 %
1"
#2121
0"
#2128
b111001010010001 )
0&
b11010100001101011 !
b11010100001101011 (
b11010100001101011 '
b11101101000101111 #
b11101101000101111 %
1"
#2135
0"
#2142
b100010000110100 )
1&
b111101000100100100 !
b111101000100100100 (
b111101000100100100 '
b1110010100111011010 #
b1110010100111011010 %
1"
#2149
0"
#2156
b101000111101101 )
1&
b1000110000111010010 !
b1000110000111010010 (
b1000110000111010010 '
b1101101100010111001 #
b1101101100010111001 %
1"
#2163
0"
#2170
b11010110111011 )
0&
b101010100001000111 !
b101010100001000111 (
b101010100001000111 '
b1100101010010011011 #
b1100101010010011011 %
1"
#2177
0"
#2184
b110111000101001 )
1&
b1111000100101001 !
b1111000100101001 (
b1111000100101001 '
b10001100000111000 #
b10001100000111000 %
1"
#2191
0"
#2198
b10010011000101 )
1&
b10010101111001100 !
b10010101111001100 (
b10010101111001100 '
b1000001001110100100 #
b1000001001110100100 %
1"
#2205
0"
#2212
b1011011101110 )
1&
b10110100011100011 !
b10110100011100011 (
b10110100011100011 '
b1111101111010010011 #
b1111101111010010011 %
1"
#2219
0"
#2226
b11101110100111 )
1&
b101010000101001101 !
b101010000101001101 (
b101010000101001101 '
b1011010010011000000 #
b1011010010011000000 %
1"
#2233
0"
#2240
b1111010010001 )
0&
b1010110011000010 !
b1010110011000010 (
b1010110011000010 '
b101101001101110101 #
b101101001101110101 %
1"
#2247
0"
#2254
b100011100000100 )
0&
b110110010111110111 !
b110110010111110111 (
b110110010111110111 '
b1100010000000001100 #
b1100010000000001100 %
1"
#2261
0"
#2268
b1000101100000 )
0&
b1010000100111111 !
b1010000100111111 (
b1010000100111111 '
b1001010001111100110 #
b1001010001111100110 %
1"
#2275
0"
#2282
b1100111011 )
0&
b10010001110 !
b10010001110 (
b10010001110 '
b1011010010000000 #
b1011010010000000 %
1"
#2289
0"
#2296
b110111101110001 )
0&
b101011011011101000 !
b101011011011101000 (
b101011011011101000 '
b110001111000101001 #
b110001111000101001 %
1"
#2303
0"
#2310
b100010001000011 )
1&
b110001110101010 !
b110001110101010 (
b110001110101010 '
b1011101011100100 #
b1011101011100100 %
1"
#2317
0"
#2324
b110111101110 )
0&
b1111100011 !
b1111100011 (
b1111100011 '
b10001110111111 #
b10001110111111 %
1"
#2331
0"
#2338
b11101101001011 )
0&
b100000111100101011 !
b100000111100101011 (
b100000111100101011 '
b1000111001000001010 #
b1000111001000001010 %
1"
#2345
0"
#2352
b10111000010010 )
0&
b10110110010110000 !
b10110110010110000 (
b10110110010110000 '
b111111010100111101 #
b111111010100111101 %
1"
#2359
0"
#2366
b100101001000100 )
1&
b101011000111010010 !
b101011000111010010 (
b101011000111010010 '
b1001010010011110000 #
b1001010010011110000 %
1"
#2373
0"
#2380
b1000111010110 )
0&
b111111011001 !
b111111011001 (
b111111011001 '
b111000110111100 #
b111000110111100 %
1"
#2387
0"
#2394
b101101100111010 )
1&
b1000101100100000011 !
b1000101100100000011 (
b1000101100100000011 '
b1100001100110101011 #
b1100001100110101011 %
1"
#2401
0"
#2408
b110100110010001 )
0&
b101101000010000010 !
b101101000010000010 (
b101101000010000010 '
b110110100110100000 #
b110110100110100000 %
1"
#2415
0"
#2422
b100010001011000 )
1&
b1000001100110101 !
b1000001100110101 (
b1000001100110101 '
b1111010110111110 #
b1111010110111110 %
1"
#2429
0"
#2436
b110000111101110 )
0&
b1000100100101110111 !
b1000100100101110111 (
b1000100100101110111 '
b1011001101001110101 #
b1011001101001110101 %
1"
#2443
0"
#2450
b11100001111011 )
1&
b1100011011011101 !
b1100011011011101 (
b1100011011011101 '
b11100001010101110 #
b11100001010101110 %
1"
#2457
0"
#2464
b110111010011111 )
1&
b11001000010110100 !
b11001000010110100 (
b11001000010110100 '
b11100111110101000 #
b11100111110101000 %
1"
#2471
0"
#2478
b111110011000100 )
0&
b1101011111011001000 !
b1101011111011001000 (
b1101011111011001000 '
b1101110101110001100 #
b1101110101110001100 %
1"
#2485
0"
#2492
b1000000001110 )
0&
b1010111111010011 !
b1010111111010011 (
b1010111111010011 '
b1010111100111010101 #
b1010111100111010101 %
1"
#2499
0"
#2506
b11101100111100 )
0&
b111010100110101100 !
b111010100110101100 (
b111010100110101100 '
b1111110101000111011 #
b1111110101000111011 %
1"
#2513
0"
#2520
b111001000010001 )
0&
b1101000100000101100 !
b1101000100000101100 (
b1101000100000101100 '
b1110101010001110000 #
b1110101010001110000 %
1"
#2527
0"
#2534
b100010000110100 )
0&
b11100000000111 !
b11100000000111 (
b11100000000111 '
b110100100100111 #
b110100100100111 %
1"
#2541
0"
